[
    {
        "Ссылка на товар": "https://www.muztorg.ru/product/A066330",
        "Ссылка на изображение": "https://www.muztorg.ru/files/8aj/no1/o5z/cow/00o/g00/4wg/4oo/8/8ajno1o5zcow00og004wg4oo8.jpg",
        "Категория товара": "Музыкальные ложки",
        "Наименование": "YARA MS-2X",
        "Артикул": "A066330",
        "Наличие": "В наличии",
        "Краткое описание": "Музыкальные ложки `Хохлома`, пара, МЛХ, осина, береза",
        "Цена": "265",
        "Цена по акции": "YARA MS-2X",
        "Начальная цена аренды в день": "Аренды нет",
        "Рейтинг": "Оценок нет",
        "Полное описание": "Нет"
    },
    {
        "Ссылка на товар": "https://www.muztorg.ru/product/A116042",
        "Ссылка на изображение": "https://www.muztorg.ru/files/62k/lho/0ji/y04/8o0/wwg/808/40w/w/62klho0jiy048o0wwg80840ww.jpeg",
        "Категория товара": "Музыкальные ложки",
        "Наименование": "Хохлома LHL6601 Деревянная ложка полубаская, роспись `Матрешка.",
        "Артикул": "A116042",
        "Наличие": "В наличии",
        "Краткое описание": "Деревянная ложка полубаская, роспись \"Матрешка\"",
        "Цена": "100",
        "Цена по акции": "Хохлома LHL6601 Деревянная ложка полубаская, роспись `Матрешка.",
        "Начальная цена аренды в день": "Аренды нет",
        "Рейтинг": "Оценок нет",
        "Полное описание": "LHL6601 Деревянная ложка полубаская, роспись \"Матрешка\", Хохлома",
        "Материал": "береза.",
        "Длина": "19см.",
        "Ширина черпачка": "6см."
    },
    {
        "Ссылка на товар": "https://www.muztorg.ru/product/A100052",
        "Ссылка на изображение": "https://www.muztorg.ru/files/8hp/nr7/t98/a88/oow/g88/48o/gow/4/8hpnr7t98a88oowg8848ogow4.jpeg",
        "Категория товара": "Музыкальные ложки",
        "Наименование": "Хохлома LHL7101 Деревянная ложка полубаская, роспись Золото",
        "Артикул": "A100052",
        "Наличие": "В наличии",
        "Краткое описание": "Деревянная ложка полубаская, роспись Золото",
        "Цена": "100",
        "Цена по акции": "Хохлома LHL7101 Деревянная ложка полубаская, роспись Золото",
        "Начальная цена аренды в день": "Аренды нет",
        "Рейтинг": "Оценок нет",
        "Полное описание": "",
        "Материал": "береза.",
        "Длина": "19 см.",
        "Ширина черпачка": "6 см."
    },
    {
        "Ссылка на товар": "https://www.muztorg.ru/product/A060868",
        "Ссылка на изображение": "https://www.muztorg.ru/files/9ud/sgu/o2y/fc4/sos/ssw/ssk/0g4/9udsguo2yfc4sossswssk0g40.jpeg",
        "Категория товара": "Музыкальные ложки",
        "Наименование": "YARA MS-2ZX",
        "Артикул": "A060868",
        "Наличие": "В наличии",
        "Краткое описание": "Музыкальные ложки `Золотая Хохлома` пара, МЛХ, материал - осина, береза",
        "Цена": "265",
        "Цена по акции": "YARA MS-2ZX",
        "Начальная цена аренды в день": "Аренды нет",
        "Рейтинг": "Оценок нет",
        "Полное описание": "Нет"
    },
    {
        "Ссылка на товар": "https://www.muztorg.ru/product/A063963",
        "Ссылка на изображение": "https://www.muztorg.ru/files/4ks/aw8/m9l/g2s/cgw/kcs/44w/o8c/o/4ksaw8m9lg2scgwkcs44wo8co.jpg",
        "Категория товара": "Музыкальные ложки",
        "Наименование": "Хохлома LHL6402 Деревянная ложка маленькая, роспись хохломская традиционная",
        "Артикул": "A063963",
        "Наличие": "\n                В наличии, по предоплате                \n\n\n\n                    Товар в наличии на центральном складе. Будет доставлен после предоплаты\n                \n",
        "Краткое описание": "Деревянная ложка маленькая, роспись хохломская традиционная",
        "Цена": "80",
        "Цена по акции": "Хохлома LHL6402 Деревянная ложка маленькая, роспись хохломская традиционная",
        "Начальная цена аренды в день": "Аренды нет",
        "Рейтинг": "Оценок нет",
        "Полное описание": "",
        "Материал": "береза.",
        "Длина": "14,7см.",
        "Ширина черпачка": "3,5см."
    },
    {
        "Ссылка на товар": "https://www.muztorg.ru/product/A116101",
        "Ссылка на изображение": "https://www.muztorg.ru/files/9ee/lvd/jn7/ig4/sg8/0c0/kck/8sk/c/9eelvdjn7ig4sg80c0kck8skc.jpeg",
        "Категория товара": "Музыкальные ложки",
        "Наименование": "Хохлома LHL6801 Ложка деревянная столовая, роспись `Краснушка.",
        "Артикул": "A116101",
        "Наличие": "В наличии",
        "Краткое описание": "Ложка деревянная столовая, роспись \"Краснушка\"",
        "Цена": "80",
        "Цена по акции": "Хохлома LHL6801 Ложка деревянная столовая, роспись `Краснушка.",
        "Начальная цена аренды в день": "Аренды нет",
        "Рейтинг": "Оценок нет",
        "Полное описание": "LHL6801 Ложка столовая \"Краснушка\", Хохлома",
        "Материал": "береза.",
        "Длина": "19см.",
        "Ширина черпачка": "6см."
    },
    {
        "Ссылка на товар": "https://www.muztorg.ru/product/A100049",
        "Ссылка на изображение": "https://www.muztorg.ru/files/dah/dhw/yw1/pss/koo/sgo/s0s/k0s/8/dahdhwyw1psskoosgos0sk0s8.jpeg",
        "Категория товара": "Музыкальные ложки",
        "Наименование": "Хохлома LHL6201 Деревянная ложка полубаская столовая, без росписи, хемпельная",
        "Артикул": "A100049",
        "Наличие": "В наличии",
        "Краткое описание": "Деревянная ложка полубаская столовая, без росписи, хемпельная",
        "Цена": "50",
        "Цена по акции": "Хохлома LHL6201 Деревянная ложка полубаская столовая, без росписи, хемпельная",
        "Начальная цена аренды в день": "Аренды нет",
        "Рейтинг": "Оценок нет",
        "Полное описание": "",
        "Материал": "береза.",
        "Длина": "19 см.",
        "Ширина черпачка": "6 см."
    },
    {
        "Ссылка на товар": "https://www.muztorg.ru/product/A100056",
        "Ссылка на изображение": "https://www.muztorg.ru/files/3je/8wt/381/2io/g04/o0o/ooc/c0o/8/3je8wt3812iog04o0ooocc0o8.jpeg",
        "Категория товара": "Музыкальные ложки",
        "Наименование": "Хохлома LHL6501 Деревянная ложка полубаская, роспись Чернушка",
        "Артикул": "A100056",
        "Наличие": "В наличии",
        "Краткое описание": "Деревянная ложка полубаская, роспись Чернушка",
        "Цена": "80",
        "Цена по акции": "Хохлома LHL6501 Деревянная ложка полубаская, роспись Чернушка",
        "Начальная цена аренды в день": "Аренды нет",
        "Рейтинг": "Оценок нет",
        "Полное описание": "",
        "Материал": "береза.",
        "Длина": "19 см.",
        "Ширина черпачка": "6 см."
    },
    {
        "Ссылка на товар": "https://www.muztorg.ru/product/A102619",
        "Ссылка на изображение": "https://www.muztorg.ru/files/9ij/iz4/j6e/eos/8kc/cgk/w4g/k4c/s/9ijiz4j6eeos8kccgkw4gk4cs.jpg",
        "Категория товара": "Музыкальные ложки",
        "Наименование": "Мастерская Сереброва бр-лж-04 Ложки в станке",
        "Артикул": "A102619",
        "Наличие": "В наличии",
        "Краткое описание": "Ложки в станке",
        "Цена": "710",
        "Цена по акции": "Мастерская Сереброва бр-лж-04 Ложки в станке",
        "Начальная цена аренды в день": "Аренды нет",
        "Рейтинг": "Оценок нет",
        "Полное описание": "Нет"
    },
    {
        "Ссылка на товар": "https://www.muztorg.ru/product/A102753",
        "Ссылка на изображение": "https://www.muztorg.ru/files/8hq/njn/sf5/y0w/oww/so8/4k4/80o/o/8hqnjnsf5y0wowwso84k480oo.jpg",
        "Категория товара": "Музыкальные ложки",
        "Наименование": "Мастерская Сереброва т2-лж-04 Ложки в станке",
        "Артикул": "A102753",
        "Наличие": "В наличии",
        "Краткое описание": "Ложки в станке",
        "Цена": "882",
        "Цена по акции": "Мастерская Сереброва т2-лж-04 Ложки в станке",
        "Начальная цена аренды в день": "Аренды нет",
        "Рейтинг": "Оценок нет",
        "Полное описание": "Нет"
    },
    {
        "Ссылка на товар": "https://www.muztorg.ru/product/A116041",
        "Ссылка на изображение": "https://www.muztorg.ru/files/axy/1ny/q3x/cwg/48c/gss/cwk/gg0/4/axy1nyq3xcwg48cgsscwkgg04.jpeg",
        "Категория товара": "Музыкальные ложки",
        "Наименование": "Хохлома LHL6401 Деревянная ложка полубаская, роспись хохломская традиционная",
        "Артикул": "A116041",
        "Наличие": "В наличии",
        "Краткое описание": "Деревянная ложка полубаская, роспись хохломская традиционная",
        "Цена": "110",
        "Цена по акции": "Хохлома LHL6401 Деревянная ложка полубаская, роспись хохломская традиционная",
        "Начальная цена аренды в день": "Аренды нет",
        "Рейтинг": "Оценок нет",
        "Полное описание": "LHL6401 Деревянная ложка полубаская, роспись хохломская традиционная, Хохлома.",
        "Материал": "береза.",
        "Длина": "19см.",
        "Ширина черпачка": "6см."
    },
    {
        "Ссылка на товар": "https://www.muztorg.ru/product/A102702",
        "Ссылка на изображение": "https://www.muztorg.ru/files/7is/fh2/mye/40s/4co/sco/cg8/8ww/4/7isfh2mye40s4coscocg88ww4.jpg",
        "Категория товара": "Музыкальные ложки",
        "Наименование": "Мастерская Сереброва к2-лж-04 Ложки в станке",
        "Артикул": "A102702",
        "Наличие": "В наличии",
        "Краткое описание": "Ложки в станке",
        "Цена": "1095",
        "Цена по акции": "Мастерская Сереброва к2-лж-04 Ложки в станке",
        "Начальная цена аренды в день": "Аренды нет",
        "Рейтинг": "Оценок нет",
        "Полное описание": "Кто и когда первый додумался превратить наши обыкновенные столовые ложки в ударный инструмент, сказать теперь совершенно невозможно. Но то, что это и прежде и теперь самый простой, самый колоритный и распространенный инструмент русского народа, — бесспорный факт.Некоторые исполнители навешивают на ложки бубенчики, украшающие цокающий перестук дополнительным звоном.",
        "Наши расписные деревянные ложки популярны не только у нас, но и за рубежом. Тысячами вывозят их иностранцы к себе домой в качестве сувениров. Еще бы": "легко, красиво, дешево и сразу «два зайца» — старинный предмет быта и он же — музыкальный инструмент. Деревянные ложки и половники можно купить в магазинах, на базарах или вырезать из сухого дерева самим. Есть народные мастера, специализирующиеся на изготовлении именно музыкальных ложек. Их изделия отличаются несколько большей толщиной, а значит, прочностью и большей звучностью; они используют лучшие породы древесины."
    },
    {
        "Ссылка на товар": "https://www.muztorg.ru/product/A099897",
        "Ссылка на изображение": "https://www.muztorg.ru/files/2v4/qzg/4js/jac/80o/swo/c84/kc8/g/2v4qzg4jsjac80oswoc84kc8g.jpeg",
        "Категория товара": "Музыкальные ложки",
        "Наименование": "Мастерская Сереброва MS-K1-LZ-07 Ложки веерные, тройка, с бубенцами, 1 категория",
        "Артикул": "A099897",
        "Наличие": "В наличии",
        "Краткое описание": "Ложки веерные, тройка, с бубенцами, 1 категория",
        "Цена": "2426",
        "Цена по акции": "Мастерская Сереброва MS-K1-LZ-07 Ложки веерные, тройка, с бубенцами, 1 категория",
        "Начальная цена аренды в день": "Аренды нет",
        "Рейтинг": "Оценок нет",
        "Полное описание": "Комплект состоит из 4 ложек.Три из них закреплены на деревянном бруске на расстоянии 35мм друг от друга, под углом в 22 градуса.В каждом черпаке закреплен бубенчик.Играют на них с помощью четвертой «игровой» обычной ложки.Для ансамблей и оркестров (1 категория).",
        "Отделка": "роспись, лак."
    },
    {
        "Ссылка на товар": "https://www.muztorg.ru/product/A102767",
        "Ссылка на изображение": "https://www.muztorg.ru/files/f1o/k8m/zzw/1wg/ogw/k08/swk/8w4/s/f1ok8mzzw1wgogwk08swk8w4s.jpg",
        "Категория товара": "Музыкальные ложки",
        "Наименование": "Мастерская Сереброва эк-лб-01 Ложка большая музыкальная",
        "Артикул": "A102767",
        "Наличие": "В наличии",
        "Краткое описание": "Ложка большая музыкальная",
        "Цена": "24973",
        "Цена по акции": "Мастерская Сереброва эк-лб-01 Ложка большая музыкальная",
        "Начальная цена аренды в день": "Аренды нет",
        "Рейтинг": "Оценок нет",
        "Полное описание": "Где моя БОЛЬШАЯ ложка?Поиграть хочу немножко.Удивить народ потехой.Закатиться звонким смехом!"
    },
    {
        "Ссылка на товар": "https://www.muztorg.ru/product/A099882",
        "Ссылка на изображение": "https://www.muztorg.ru/files/qfk/lbk/8ou/68w/480/ckw/888/4os/qfklbk8ou68w480ckw8884os.jpg",
        "Категория товара": "Музыкальные ложки",
        "Наименование": "Мастерская Сереброва MS-K1-LZ-05 Ложки в станке с бубенцами, 1 категория",
        "Артикул": "A099882",
        "Наличие": "В наличии",
        "Краткое описание": "Ложки в станке с бубенцами, 1 категория",
        "Цена": "1509",
        "Цена по акции": "Мастерская Сереброва MS-K1-LZ-05 Ложки в станке с бубенцами, 1 категория",
        "Начальная цена аренды в день": "Аренды нет",
        "Рейтинг": "Оценок нет",
        "Полное описание": "Две деревянные соединенные между собой ложки с бубенцами.Хвостовики черенков сточены под углом в 45 градусов.Для ансамблей и оркестров (1 категория).",
        "Соединение": "кольцо из хлорвинила, диаметр 20мм.",
        "Отделка": "роспись, лак."
    },
    {
        "Ссылка на товар": "https://www.muztorg.ru/product/A100047",
        "Ссылка на изображение": "https://www.muztorg.ru/files/22i/d1g/v07/91c/8g0/8wo/gk0/ogk/g/22id1gv0791c8g08wogk0ogkg.jpeg",
        "Категория товара": "Музыкальные ложки",
        "Наименование": "Хохлома LHL6102 Деревянная ложка маленькая, фрезерная, без росписи",
        "Артикул": "A100047",
        "Наличие": "В наличии",
        "Краткое описание": "Деревянная ложка маленькая, фрезерная, без росписи",
        "Цена": "30",
        "Цена по акции": "Хохлома LHL6102 Деревянная ложка маленькая, фрезерная, без росписи",
        "Начальная цена аренды в день": "Аренды нет",
        "Рейтинг": "Оценок нет",
        "Полное описание": "",
        "Материал": "береза.",
        "Длина": "14,7 см.",
        "Ширина черпачка": "3,5 см."
    },
    {
        "Ссылка на товар": "https://www.muztorg.ru/product/A100048",
        "Ссылка на изображение": "https://www.muztorg.ru/files/3dc/w38/q03/yqs/sk0/cck/gko/4wo/k/3dcw38q03yqssk0cckgko4wok.jpeg",
        "Категория товара": "Музыкальные ложки",
        "Наименование": "Хохлома LHL6101 Деревянная ложка полубаская столовая, без росписи, фрезерная",
        "Артикул": "A100048",
        "Наличие": "В наличии",
        "Краткое описание": "Деревянная ложка полубаская столовая, без росписи, фрезерная",
        "Цена": "50",
        "Цена по акции": "Хохлома LHL6101 Деревянная ложка полубаская столовая, без росписи, фрезерная",
        "Начальная цена аренды в день": "Аренды нет",
        "Рейтинг": "Оценок нет",
        "Полное описание": "",
        "Материал": "береза.",
        "Длина": "19 см.",
        "Ширина черпачка": "6 см."
    },
    {
        "Ссылка на товар": "https://www.muztorg.ru/product/A099878",
        "Ссылка на изображение": "https://www.muztorg.ru/files/c5i/dlx/7xi/x44/cgo/k84/8o8/4s8/c/c5idlx7xix44cgok848o84s8c.jpg",
        "Категория товара": "Музыкальные ложки",
        "Наименование": "Мастерская Сереброва MS-K2-LZ-02 Ложка с бубенцом",
        "Артикул": "A099878",
        "Наличие": "\n                В наличии, по предоплате                \n\n\n\n                    Товар в наличии на центральном складе. Будет доставлен после предоплаты\n                \n",
        "Краткое описание": "Ложка с бубенцом",
        "Цена": "334",
        "Цена по акции": "Мастерская Сереброва MS-K2-LZ-02 Ложка с бубенцом",
        "Начальная цена аренды в день": "Аренды нет",
        "Рейтинг": "Оценок нет",
        "Полное описание": "Деревянная ложка с металлическим бубенцом.Диаметр черпака 58 мм.Длина черенка 115 мм.Для дошкольников и детей младшего школьного возраста.",
        "Отделка": "роспись, лак."
    },
    {
        "Ссылка на товар": "https://www.muztorg.ru/product/A099883",
        "Ссылка на изображение": "https://www.muztorg.ru/files/5u5/wwv/9cz/hoo/0w4/oos/g4c/4cw/s/5u5wwv9czhoo0w4oosg4c4cws.jpg",
        "Категория товара": "Музыкальные ложки",
        "Наименование": "Мастерская Сереброва MS-T2-LZ-05 Ложки в станке с бубенцами, тонировка",
        "Артикул": "A099883",
        "Наличие": "В наличии",
        "Краткое описание": "Ложки в станке с бубенцами, тонировка",
        "Цена": "979",
        "Цена по акции": "Мастерская Сереброва MS-T2-LZ-05 Ложки в станке с бубенцами, тонировка",
        "Начальная цена аренды в день": "Аренды нет",
        "Рейтинг": "Оценок нет",
        "Полное описание": "Две деревянные соединенные между собой ложки с бубенцами.Хвостовики черенков сточены под углом в 45 градусов.Для дошкольников и детей младшего школьного возраста.",
        "Соединение": "кольцо из хлорвинила, диаметр 20мм.",
        "Отделка": "тонировка."
    },
    {
        "Ссылка на товар": "https://www.muztorg.ru/product/A102618",
        "Ссылка на изображение": "https://www.muztorg.ru/files/alj/3y8/6v5/gws/swc/8k0/cc4/ko0/g/alj3y86v5gwsswc8k0cc4ko0g.jpg",
        "Категория товара": "Музыкальные ложки",
        "Наименование": "Мастерская Сереброва бр-лж-02 Ложка берёзовая с бубенцом",
        "Артикул": "A102618",
        "Наличие": "В наличии",
        "Краткое описание": "Ложка берёзовая с бубенцом",
        "Цена": "235",
        "Цена по акции": "Мастерская Сереброва бр-лж-02 Ложка берёзовая с бубенцом",
        "Начальная цена аренды в день": "Аренды нет",
        "Рейтинг": "Оценок нет",
        "Полное описание": "Обычно в игре одного исполнителя используются три ложки. Две из них закладываются между пальцами левой руки, третья берется в правую. Первые две служат как бы двойной «наковальней», по которой бьют третьей ложкой. Причем бьют скользящим ударом с одной чашечки на другую, тут же еще раз прихлопывая ими при помощи пальцев левой руки. Получается все время многозвучный ажурный ритмический рисунок. Иногда, при игре сидя, в ногах зажимают два-три, а то и четыре половника, по которым также периодически ударяют ложкой или проводят ею глиссандо.Освоение игры на ложках требует некоторого труда и терпения. Разучивать тот или иной, особенно сложный, ритмический рисунок следует вначале медленно, добиваясь автоматизма в движениях. Описанная выше хватка является основной, но не единственной. Мастера-виртуозы очень ловко и разнообразно чередуют удары правой руки о левую, левой о колено или плечо в сочетании с ударами по половникам. Ложечник В. С. Морозов, артист оркестра хора им. Пятницкого, за свою неподражаемую игру на ложках и других народных инструментах был удостоен почетного звания заслуженного артиста РСФСР. Мастерство даже в таком, казалось бы, шуточном деле всегда высоко ценится нашим народом.",
        "Кто и когда первый додумался превратить наши обыкновенные столовые ложки в ударный инструмент, сказать теперь совершенно невозможно. Но то, что это и прежде и теперь самый простой, самый колоритный и распространенный инструмент русского народа, — бесспорный факт. Наши расписные деревянные ложки популярны не только у нас, но и за рубежом. Тысячами вывозят их иностранцы к себе домой в качестве сувениров. Еще бы": "легко, красиво, дешево и сразу «два зайца» — старинный предмет быта и он же — музыкальный инструмент. Деревянные ложки и половники можно купить в магазинах, на базарах или вырезать из сухого дерева самим. Есть народные мастера, специализирующиеся на изготовлении именно музыкальных ложек. Их изделия отличаются несколько большей толщиной, а значит, прочностью и большей звучностью; они используют лучшие породы древесины. Некоторые исполнители навешивают на ложки бубенчики, украшающие цокающий перестук дополнительным звоном."
    },
    {
        "Ссылка на товар": "https://www.muztorg.ru/product/A102712",
        "Ссылка на изображение": "https://www.muztorg.ru/files/8ku/8tr/ipk/kws/0cw/8gs/40k/480/4/8ku8tripkkws0cw8gs40k4804.jpg",
        "Категория товара": "Музыкальные ложки",
        "Наименование": "Мастерская Сереброва кп-лж-01 Ложка малая",
        "Артикул": "A102712",
        "Наличие": "В наличии",
        "Краткое описание": "Ложка малая",
        "Цена": "108",
        "Цена по акции": "Мастерская Сереброва кп-лж-01 Ложка малая",
        "Начальная цена аренды в день": "Аренды нет",
        "Рейтинг": "Оценок нет",
        "Полное описание": "Ложка деревянная размером с чайную ложку 14 см х 3,5 см"
    },
    {
        "Ссылка на товар": "https://www.muztorg.ru/product/A099886",
        "Ссылка на изображение": "https://www.muztorg.ru/files/1mk/6u7/6xm/1z4/88o/444/sgc/08s/g/1mk6u76xm1z488o444sgc08sg.jpg",
        "Категория товара": "Музыкальные ложки",
        "Наименование": "Мастерская Сереброва MS-T1-LZ-04 Ложки в станке, тонировка, 1 категория",
        "Артикул": "A099886",
        "Наличие": "В наличии",
        "Краткое описание": "Ложки в станке, тонировка, 1 категория",
        "Цена": "1121",
        "Цена по акции": "Мастерская Сереброва MS-T1-LZ-04 Ложки в станке, тонировка, 1 категория",
        "Начальная цена аренды в день": "Аренды нет",
        "Рейтинг": "Оценок нет",
        "Полное описание": "Две деревянные соединенные между собой ложки.Хвостовики черенков сточены под углом в 45 градусов.Для ансамблей и оркестров (1 категория).",
        "Соединение": "кольцо из хлорвинила, диаметр 20мм.",
        "Отделка": "тонировка."
    },
    {
        "Ссылка на товар": "https://www.muztorg.ru/product/A099888",
        "Ссылка на изображение": "https://www.muztorg.ru/files/4hw/cr8/a52/fi8/0s0/48k/coo/w0s/s/4hwcr8a52fi80s048kcoow0ss.jpg",
        "Категория товара": "Музыкальные ложки",
        "Наименование": "Мастерская Сереброва MS-K2-LZ-07 Ложки веерные с бубенцами",
        "Артикул": "A099888",
        "Наличие": "В наличии",
        "Краткое описание": "Ложки веерные с бубенцами",
        "Цена": "1644",
        "Цена по акции": "Мастерская Сереброва MS-K2-LZ-07 Ложки веерные с бубенцами",
        "Начальная цена аренды в день": "Аренды нет",
        "Рейтинг": "Оценок нет",
        "Полное описание": "Комплект состоит из 4 ложек.Три из них закреплены на деревянном бруске на расстоянии 35мм друг от друга, под углом в 22 градуса.В черпачки ложек установлены бубенцы.Играют на них с помощью четвертой «игровой» обычной ложки без бубенца.Для дошкольников и детей младшего школьного возраста.",
        "Отделка": "роспись, лак."
    },
    {
        "Ссылка на товар": "https://www.muztorg.ru/product/A102617",
        "Ссылка на изображение": "https://www.muztorg.ru/files/85m/za7/9nu/u4g/gc4/kkg/cws/wgo/g/85mza79nuu4ggc4kkgcwswgog.jpg",
        "Категория товара": "Музыкальные ложки",
        "Наименование": "Мастерская Сереброва бр-лж-01 Ложка берёзовая",
        "Артикул": "A102617",
        "Наличие": "В наличии",
        "Краткое описание": "Ложка берёзовая",
        "Цена": "204",
        "Цена по акции": "Мастерская Сереброва бр-лж-01 Ложка берёзовая",
        "Начальная цена аренды в день": "Аренды нет",
        "Рейтинг": "Оценок нет",
        "Полное описание": "Есть народные мастера, специализирующиеся на изготовлении именно музыкальных ложек. Их изделия отличаются несколько большей толщиной, а значит, прочностью и большей звучностью; они используют лучшие породы древесины. Именно такие ложки изготавливает Мастерская Сереброва."
    },
    {
        "Ссылка на товар": "https://www.muztorg.ru/product/A085332",
        "Ссылка на изображение": "https://www.muztorg.ru/files/7dd/anw/vwp/esk/go4/sw0/0c0/g0o/g/7ddanwvwpeskgo4sw00c0g0og.jpeg",
        "Категория товара": "Музыкальные ложки",
        "Наименование": "Мастерская Сереброва MS-T1-LZ-02 Ложка с бубенцом, тонировка, 1 категория",
        "Артикул": "A085332",
        "Наличие": "В наличии",
        "Краткое описание": "",
        "Цена": "489",
        "Цена по акции": "Мастерская Сереброва MS-T1-LZ-02 Ложка с бубенцом, тонировка, 1 категория",
        "Начальная цена аренды в день": "Аренды нет",
        "Рейтинг": "Оценок нет",
        "Полное описание": "Деревянная ложка с металлическим бубенцом.Диаметр черпака 58 мм.Длина черенка 115 мм.Для ансамблей и оркестров (1 категория).",
        "Отделка": "тонировка."
    },
    {
        "Ссылка на товар": "https://www.muztorg.ru/product/A099879",
        "Ссылка на изображение": "https://www.muztorg.ru/files/ezt/yrv/5lo/tcg/oc8/wko/wk0/0s0/o/eztyrv5lotcgoc8wkowk00s0o.jpeg",
        "Категория товара": "Музыкальные ложки",
        "Наименование": "Мастерская Сереброва MS-K1-LZ-02 Ложка с бубенцом, 1 категория",
        "Артикул": "A099879",
        "Наличие": "В наличии",
        "Краткое описание": "Ложка с бубенцом, 1 категория",
        "Цена": "547",
        "Цена по акции": "Мастерская Сереброва MS-K1-LZ-02 Ложка с бубенцом, 1 категория",
        "Начальная цена аренды в день": "Аренды нет",
        "Рейтинг": "Оценок нет",
        "Полное описание": "Деревянная ложка с металлическим бубенцом.Диаметр черпака 58 мм.Длина черенка 115 мм.Для ансамблей и оркестров (1 категория).",
        "Отделка": "роспись, лак."
    },
    {
        "Ссылка на товар": "https://www.muztorg.ru/product/A099880",
        "Ссылка на изображение": "Нет изображения",
        "Категория товара": "Музыкальные ложки",
        "Наименование": "Мастерская Сереброва MS-T2-LZ-02 Ложка с бубенцом, тонировка",
        "Артикул": "A099880",
        "Наличие": "В наличии",
        "Краткое описание": "Ложка с бубенцом, тонировка",
        "Цена": "298",
        "Цена по акции": "Мастерская Сереброва MS-T2-LZ-02 Ложка с бубенцом, тонировка",
        "Начальная цена аренды в день": "Аренды нет",
        "Рейтинг": "Оценок нет",
        "Полное описание": "Деревянная ложка с металлическим бубенцом.Диаметр черпака 58 мм.Длина черенка 115 мм.Для дошкольников и детей младшего школьного возраста.",
        "Отделка": "тонировка."
    },
    {
        "Ссылка на товар": "https://www.muztorg.ru/product/A099881",
        "Ссылка на изображение": "https://www.muztorg.ru/files/2jt/p0i/d6s/l0k/ckg/wc0/gwo/c48/s/2jtp0id6sl0kckgwc0gwoc48s.jpg",
        "Категория товара": "Музыкальные ложки",
        "Наименование": "Мастерская Сереброва MS-K2-LZ-05 Ложки в станке с бубенцами",
        "Артикул": "A099881",
        "Наличие": "В наличии",
        "Краткое описание": "Ложки в станке с бубенцами",
        "Цена": "1210",
        "Цена по акции": "Мастерская Сереброва MS-K2-LZ-05 Ложки в станке с бубенцами",
        "Начальная цена аренды в день": "Аренды нет",
        "Рейтинг": "Оценок нет",
        "Полное описание": "Две деревянные соединенные между собой ложки с бубенцами.Хвостовики черенков сточены под углом в 45 градусов.Для дошкольников и детей младшего школьного возраста.У хохломских ложек лак запекается в печи, на выходе покрытие ложки становится более твердым и прочным.Такие ложки звучат ярче и более износостойкие.",
        "Соединение": "кольцо из хлорвинила, диаметр 20мм.",
        "Отделка": "роспись, лак.",
        "Цветовая гамма хохломских ложек": "золотые, красные, черные."
    },
    {
        "Ссылка на товар": "https://www.muztorg.ru/product/A099884",
        "Ссылка на изображение": "https://www.muztorg.ru/files/5k2/fuh/nkd/yww/ww8/0so/844/4og/4/5k2fuhnkdywwww80so8444og4.jpg",
        "Категория товара": "Музыкальные ложки",
        "Наименование": "Мастерская Сереброва MS-T1-LZ-05 Ложки в станке с бубенцами, тонировка, 1 категория",
        "Артикул": "A099884",
        "Наличие": "В наличии",
        "Краткое описание": "Ложки в станке с бубенцами, тонировка, 1 категория",
        "Цена": "1201",
        "Цена по акции": "Мастерская Сереброва MS-T1-LZ-05 Ложки в станке с бубенцами, тонировка, 1 категория",
        "Начальная цена аренды в день": "Аренды нет",
        "Рейтинг": "Оценок нет",
        "Полное описание": "Две деревянные соединенные между собой ложки с бубенцами.Хвостовики черенков сточены под углом в 45 градусов.Для ансамблей и оркестров (1 категория).",
        "Соединение": "кольцо из хлорвинила, диаметр 20мм.",
        "Отделка": "тонировка."
    },
    {
        "Ссылка на товар": "https://www.muztorg.ru/product/A099885",
        "Ссылка на изображение": "https://www.muztorg.ru/files/b41/ap7/fv5/340/48s/k08/cgk/gcc/w/b41ap7fv534048sk08cgkgccw.jpeg",
        "Категория товара": "Музыкальные ложки",
        "Наименование": "Мастерская Сереброва MS-K1-LZ-04 Ложки в станке, 1 категория",
        "Артикул": "A099885",
        "Наличие": "В наличии",
        "Краткое описание": "Ложки в станке, 1 категория",
        "Цена": "1408",
        "Цена по акции": "Мастерская Сереброва MS-K1-LZ-04 Ложки в станке, 1 категория",
        "Начальная цена аренды в день": "Аренды нет",
        "Рейтинг": "Оценок нет",
        "Полное описание": "Две деревянные соединенные между собой ложки.Хвостовики черенков сточены под углом в 45 градусов.Для ансамблей и оркестров (1 категория).",
        "Соединение": "кольцо из хлорвинила, диаметр 20мм.",
        "Отделка": "роспись, лак."
    },
    {
        "Ссылка на товар": "https://www.muztorg.ru/product/A099887",
        "Ссылка на изображение": "https://www.muztorg.ru/files/76s/k5l/l7f/ds0/ock/oow/88w/c84/s/76sk5ll7fds0ockoow88wc84s.jpg",
        "Категория товара": "Музыкальные ложки",
        "Наименование": "Мастерская Сереброва MS-K2-LZ-06 Ложки веерные",
        "Артикул": "A099887",
        "Наличие": "В наличии",
        "Краткое описание": "Ложки веерные",
        "Цена": "1525",
        "Цена по акции": "Мастерская Сереброва MS-K2-LZ-06 Ложки веерные",
        "Начальная цена аренды в день": "Аренды нет",
        "Рейтинг": "Оценок нет",
        "Полное описание": "Комплект состоит из 4 ложек.Три из них закреплены на деревянном бруске на расстоянии 35мм друг от друга, под углом в 22 градуса.Играют на них с помощью четвертой «игровой» обычной ложки.Для дошкольников и детей младшего школьного возраста.",
        "Отделка": "роспись, лак."
    },
    {
        "Ссылка на товар": "https://www.muztorg.ru/product/A099889",
        "Ссылка на изображение": "Нет изображения",
        "Категория товара": "Музыкальные ложки",
        "Наименование": "Мастерская Сереброва MS-T2-LZ-07 Ложки веерные с бубенцами, тонировка",
        "Артикул": "A099889",
        "Наличие": "В наличии",
        "Краткое описание": "Ложки веерные с бубенцами, тонировка",
        "Цена": "1313",
        "Цена по акции": "Мастерская Сереброва MS-T2-LZ-07 Ложки веерные с бубенцами, тонировка",
        "Начальная цена аренды в день": "Аренды нет",
        "Рейтинг": "Оценок нет",
        "Полное описание": "Комплект состоит из 4 ложек, с бубенцами.Три из них закреплены на деревянном бруске на расстоянии 35мм друг от друга, под углом в 22 градуса.Играют на них с помощью четвертой «игровой» обычной ложки.Для дошкольников и детей младшего школьного возраста.",
        "Отделка": "тонировка."
    },
    {
        "Ссылка на товар": "https://www.muztorg.ru/product/A099890",
        "Ссылка на изображение": "https://www.muztorg.ru/files/egr/ujd/u3f/o08/4wc/g8o/sos/w80/k/egrujdu3fo084wcg8ososw80k.jpeg",
        "Категория товара": "Музыкальные ложки",
        "Наименование": "Мастерская Сереброва MS-K1-LZ-08 Ложки веерные, пятерка, 1 категория",
        "Артикул": "A099890",
        "Наличие": "В наличии",
        "Краткое описание": "Ложки веерные, пятерка, 1 категория",
        "Цена": "3450",
        "Цена по акции": "Мастерская Сереброва MS-K1-LZ-08 Ложки веерные, пятерка, 1 категория",
        "Начальная цена аренды в день": "Аренды нет",
        "Рейтинг": "Оценок нет",
        "Полное описание": "Комплект состоит из 6 ложек.Пять из них закреплены на деревянном бруске на расстоянии 35мм друг от друга, под углом в 22 градуса.Играют на них с помощью шестой «игровой» обычной ложки.Для ансамблей и оркестров (1 категория).",
        "Отделка": "роспись, лак."
    },
    {
        "Ссылка на товар": "https://www.muztorg.ru/product/A099891",
        "Ссылка на изображение": "https://www.muztorg.ru/files/buv/a7o/t52/j48/w84/c0g/8k8/wkk/o/buva7ot52j48w84c0g8k8wkko.jpeg",
        "Категория товара": "Музыкальные ложки",
        "Наименование": "Мастерская Сереброва MS-K1-LZ-09 Ложки веерные, пятерка, с бубенцами, 1 категория",
        "Артикул": "A099891",
        "Наличие": "В наличии",
        "Краткое описание": "Ложки веерные, пятерка, с бубенцами, 1 категория",
        "Цена": "3756",
        "Цена по акции": "Мастерская Сереброва MS-K1-LZ-09 Ложки веерные, пятерка, с бубенцами, 1 категория",
        "Начальная цена аренды в день": "Аренды нет",
        "Рейтинг": "Оценок нет",
        "Полное описание": "Комплект состоит из 6 ложек.Пять из них закреплены на деревянном бруске на расстоянии 35мм друг от друга, под углом в 22 градуса.В каждом черпаке закреплен бубенчик.Играют на них с помощью шестой «игровой» обычной ложки.Для ансамблей и оркестров (1 категория).",
        "Отделка": "роспись, лак."
    },
    {
        "Ссылка на товар": "https://www.muztorg.ru/product/A099892",
        "Ссылка на изображение": "https://www.muztorg.ru/files/d4r/io9/o0l/fwo/gok/kk0/gcw/c8g/k/d4rio9o0lfwogokkk0gcwc8gk.jpeg",
        "Категория товара": "Музыкальные ложки",
        "Наименование": "Мастерская Сереброва MS-T1-LZ-09 Ложки веерные, пятерка, с бубенцами, тонировка, 1 категория",
        "Артикул": "A099892",
        "Наличие": "В наличии",
        "Краткое описание": "Ложки веерные, пятерка, с бубенцами, тонировка, 1 категория",
        "Цена": "2988",
        "Цена по акции": "Мастерская Сереброва MS-T1-LZ-09 Ложки веерные, пятерка, с бубенцами, тонировка, 1 категория",
        "Начальная цена аренды в день": "Аренды нет",
        "Рейтинг": "Оценок нет",
        "Полное описание": "Комплект состоит из 6 ложек.Пять из них закреплены на деревянном бруске на расстоянии 35мм друг от друга, под углом в 22 градуса.В каждом черпаке закреплен бубенчик.Играют на них с помощью шестой «игровой» обычной ложки.Для ансамблей и оркестров (1 категория).",
        "Отделка": "тонировка."
    },
    {
        "Ссылка на товар": "https://www.muztorg.ru/product/A099893",
        "Ссылка на изображение": "https://www.muztorg.ru/files/dv9/f1y/aqu/cgk/cog/0gg/wkw/8o0/w/dv9f1yaqucgkcog0ggwkw8o0w.jpeg",
        "Категория товара": "Музыкальные ложки",
        "Наименование": "Мастерская Сереброва MS-T1-LZ-08 Ложки веерные, пятерка, тонировка, 1 категория",
        "Артикул": "A099893",
        "Наличие": "В наличии",
        "Краткое описание": "Ложки веерные, пятерка, тонировка, 1 категория",
        "Цена": "2765",
        "Цена по акции": "Мастерская Сереброва MS-T1-LZ-08 Ложки веерные, пятерка, тонировка, 1 категория",
        "Начальная цена аренды в день": "Аренды нет",
        "Рейтинг": "Оценок нет",
        "Полное описание": "Комплект состоит из 6 ложек.Пять из них закреплены на деревянном бруске на расстоянии 35мм друг от друга, под углом в 22 градуса.Играют на них с помощью шестой «игровой» обычной ложки.Для ансамблей и оркестров (1 категория).",
        "Отделка": "тонировка."
    },
    {
        "Ссылка на товар": "https://www.muztorg.ru/product/A099894",
        "Ссылка на изображение": "https://www.muztorg.ru/files/ka0/k0y/f65/pwc/0ko/ckg/0k4/oks/ka0k0yf65pwc0kockg0k4oks.jpeg",
        "Категория товара": "Музыкальные ложки",
        "Наименование": "Мастерская Сереброва MS-T2-LZ-06 Ложки веерные, тонировка",
        "Артикул": "A099894",
        "Наличие": "В наличии",
        "Краткое описание": "Ложки веерные, тонировка",
        "Цена": "1231",
        "Цена по акции": "Мастерская Сереброва MS-T2-LZ-06 Ложки веерные, тонировка",
        "Начальная цена аренды в день": "Аренды нет",
        "Рейтинг": "Оценок нет",
        "Полное описание": "Комплект состоит из 4 ложек.Три из них закреплены на деревянном бруске на расстоянии 35мм друг от друга, под углом в 22 градуса.Играют на них с помощью четвертой «игровой» обычной ложки.Для дошкольников и детей младшего школьного возраста.",
        "Отделка": "тонировка."
    },
    {
        "Ссылка на товар": "https://www.muztorg.ru/product/A099895",
        "Ссылка на изображение": "https://www.muztorg.ru/files/bcq/c1p/pdv/bc4/sgw/gkk/gw0/wws/bcqc1ppdvbc4sgwgkkgw0wws.jpeg",
        "Категория товара": "Музыкальные ложки",
        "Наименование": "Мастерская Сереброва MS-T1-LZ-06 Ложки веерные, тонировка, 1 категория",
        "Артикул": "A099895",
        "Наличие": "В наличии",
        "Краткое описание": "Ложки веерные, тонировка, 1 категория",
        "Цена": "1803",
        "Цена по акции": "Мастерская Сереброва MS-T1-LZ-06 Ложки веерные, тонировка, 1 категория",
        "Начальная цена аренды в день": "Аренды нет",
        "Рейтинг": "Оценок нет",
        "Полное описание": "Комплект состоит из 4 ложек.Три из них закреплены на деревянном бруске на расстоянии 35мм друг от друга, под углом в 22 градуса.Играют на них с помощью четвертой «игровой» обычной ложки.Для ансамблей и оркестров (1 категория).",
        "Отделка": "тонировка."
    },
    {
        "Ссылка на товар": "https://www.muztorg.ru/product/A099896",
        "Ссылка на изображение": "https://www.muztorg.ru/files/1ig/zzj/sp7/q80/sc8/480/000/gc8/w/1igzzjsp7q80sc8480000gc8w.jpeg",
        "Категория товара": "Музыкальные ложки",
        "Наименование": "Мастерская Сереброва MS-K1-LZ-06 Ложки веерные, тройка, 1 категория",
        "Артикул": "A099896",
        "Наличие": "В наличии",
        "Краткое описание": "Ложки веерные, тройка, 1 категория",
        "Цена": "2267",
        "Цена по акции": "Мастерская Сереброва MS-K1-LZ-06 Ложки веерные, тройка, 1 категория",
        "Начальная цена аренды в день": "Аренды нет",
        "Рейтинг": "Оценок нет",
        "Полное описание": "Комплект состоит из 4 ложек.Три из них закреплены на деревянном бруске на расстоянии 35мм друг от друга, под углом в 22 градуса.Играют на них с помощью четвертой «игровой» обычной ложки.Для ансамблей и оркестров (1 категория).",
        "Отделка": "роспись, лак."
    },
    {
        "Ссылка на товар": "https://www.muztorg.ru/product/A099963",
        "Ссылка на изображение": "https://www.muztorg.ru/files/344/f9j/rte/ruo/8o4/ws4/gcs/kw0/344f9jrteruo8o4ws4gcskw00.jpg",
        "Категория товара": "Музыкальные ложки",
        "Наименование": "Мастерская Сереброва MS-T1-LZ-07 Ложки веерные с бубенцами, тонировка, 1 категория",
        "Артикул": "A099963",
        "Наличие": "В наличии",
        "Краткое описание": "Ложки веерные с бубенцами, тонировка, 1 категория",
        "Цена": "1931",
        "Цена по акции": "Мастерская Сереброва MS-T1-LZ-07 Ложки веерные с бубенцами, тонировка, 1 категория",
        "Начальная цена аренды в день": "Аренды нет",
        "Рейтинг": "Оценок нет",
        "Полное описание": "Комплект состоит из 4 ложек, с бубенцами.Три из них закреплены на деревянном бруске на расстоянии 35мм друг от друга, под углом в 22 градуса.Играют на них с помощью четвертой «игровой» обычной ложки.Для ансамблей и оркестров (1 категория).",
        "Отделка": "тонировка."
    },
    {
        "Ссылка на товар": "https://www.muztorg.ru/product/A100050",
        "Ссылка на изображение": "https://www.muztorg.ru/files/aqc/o2q/adc/408/8gs/oc8/cs4/c0g/8/aqco2qadc4088gsoc8cs4c0g8.jpeg",
        "Категория товара": "Музыкальные ложки",
        "Наименование": "Хохлома LHL8102 Деревянная ложка полубаская, роспись Дед Мороз",
        "Артикул": "A100050",
        "Наличие": "В наличии",
        "Краткое описание": "Деревянная ложка полубаская, роспись Дед Мороз",
        "Цена": "110",
        "Цена по акции": "Хохлома LHL8102 Деревянная ложка полубаская, роспись Дед Мороз",
        "Начальная цена аренды в день": "Аренды нет",
        "Рейтинг": "Оценок нет",
        "Полное описание": "",
        "Материал": "береза.",
        "Длина": "19 см.",
        "Ширина черпачка": "6 см."
    },
    {
        "Ссылка на товар": "https://www.muztorg.ru/product/A100051",
        "Ссылка на изображение": "https://www.muztorg.ru/files/94t/4hq/mun/p4w/cws/os0/w80/48c/w/94t4hqmunp4wcwsos0w8048cw.jpeg",
        "Категория товара": "Музыкальные ложки",
        "Наименование": "Хохлома LHL6704 Деревянная ложка полубаская, роспись Заяц",
        "Артикул": "A100051",
        "Наличие": "В наличии",
        "Краткое описание": "Деревянная ложка полубаская, роспись Заяц",
        "Цена": "110",
        "Цена по акции": "Хохлома LHL6704 Деревянная ложка полубаская, роспись Заяц",
        "Начальная цена аренды в день": "Аренды нет",
        "Рейтинг": "Оценок нет",
        "Полное описание": "",
        "Материал": "береза.",
        "Длина": "19 см.",
        "Ширина черпачка": "6 см."
    },
    {
        "Ссылка на товар": "https://www.muztorg.ru/product/A100053",
        "Ссылка на изображение": "https://www.muztorg.ru/files/dwc/3i2/xpm/zcc/k4c/ksw/8c8/w4s/w/dwc3i2xpmzcck4cksw8c8w4sw.jpeg",
        "Категория товара": "Музыкальные ложки",
        "Наименование": "Хохлома LHL6702 Деревянная ложка полубаская, роспись Лунтик",
        "Артикул": "A100053",
        "Наличие": "В наличии",
        "Краткое описание": "Деревянная ложка полубаская, роспись Лунтик",
        "Цена": "50",
        "Цена по акции": "Хохлома LHL6702 Деревянная ложка полубаская, роспись Лунтик",
        "Начальная цена аренды в день": "Аренды нет",
        "Рейтинг": "Оценок нет",
        "Полное описание": "",
        "Материал": "береза.",
        "Длина": "19 см.",
        "Ширина черпачка": "6 см."
    },
    {
        "Ссылка на товар": "https://www.muztorg.ru/product/A100054",
        "Ссылка на изображение": "https://www.muztorg.ru/files/5wa/rnf/pwh/yko/kwo/kgg/0os/0g0/k/5warnfpwhykokwokgg0os0g0k.jpeg",
        "Категория товара": "Музыкальные ложки",
        "Наименование": "Хохлома LHL6701 Деревянная ложка полубаская, роспись Ну, погоди.",
        "Артикул": "A100054",
        "Наличие": "В наличии",
        "Краткое описание": "Деревянная ложка полубаская, роспись Ну, погоди.",
        "Цена": "110",
        "Цена по акции": "Хохлома LHL6701 Деревянная ложка полубаская, роспись Ну, погоди.",
        "Начальная цена аренды в день": "Аренды нет",
        "Рейтинг": "Оценок нет",
        "Полное описание": "",
        "Материал": "береза.",
        "Длина": "19 см.",
        "Ширина черпачка": "6 см."
    },
    {
        "Ссылка на товар": "https://www.muztorg.ru/product/A100055",
        "Ссылка на изображение": "https://www.muztorg.ru/files/4z8/c0o/ux1/k00/s80/gs8/o8w/0gw/o/4z8c0oux1k00s80gs8o8w0gwo.jpeg",
        "Категория товара": "Без категории",
        "Наименование": "Хохлома LHL8101 Деревянная ложка полубаская, роспись Снегурочка",
        "Артикул": "A100055",
        "Наличие": "В наличии",
        "Краткое описание": "Деревянная ложка полубаская, роспись Снегурочка",
        "Цена": "110",
        "Цена по акции": "Хохлома LHL8101 Деревянная ложка полубаская, роспись Снегурочка",
        "Начальная цена аренды в день": "Аренды нет",
        "Рейтинг": "Оценок нет",
        "Полное описание": "",
        "Материал": "береза.",
        "Длина": "19 см.",
        "Ширина черпачка": "6 см."
    },
    {
        "Ссылка на товар": "https://www.muztorg.ru/product/A100057",
        "Ссылка на изображение": "Нет изображения",
        "Категория товара": "Музыкальные ложки",
        "Наименование": "Хохлома LHL7201 Ложка деревянная столовая, роспись Зеленушка",
        "Артикул": "A100057",
        "Наличие": "В наличии",
        "Краткое описание": "Ложка деревянная столовая, роспись Зеленушка",
        "Цена": "70",
        "Цена по акции": "Хохлома LHL7201 Ложка деревянная столовая, роспись Зеленушка",
        "Начальная цена аренды в день": "Аренды нет",
        "Рейтинг": "Оценок нет",
        "Полное описание": "",
        "Материал": "береза.",
        "Длина": "19 см.",
        "Ширина черпачка": "6 см."
    },
    {
        "Ссылка на товар": "https://www.muztorg.ru/product/A102620",
        "Ссылка на изображение": "https://www.muztorg.ru/files/1tl/1ny/a12/h0k/ssw/ko4/4gg/8co/c/1tl1nya12h0ksswko44gg8coc.jpg",
        "Категория товара": "Музыкальные ложки",
        "Наименование": "Мастерская Сереброва бр-лж-05 Ложки в станке с бубенцами",
        "Артикул": "A102620",
        "Наличие": "В наличии",
        "Краткое описание": "Ложки в станке с бубенцами",
        "Цена": "785",
        "Цена по акции": "Мастерская Сереброва бр-лж-05 Ложки в станке с бубенцами",
        "Начальная цена аренды в день": "Аренды нет",
        "Рейтинг": "Оценок нет",
        "Полное описание": "",
        "Кто и когда первый додумался превратить наши обыкновенные столовые ложки в ударный инструмент, сказать теперь совершенно невозможно. Но то, что это и прежде и теперь самый простой, самый колоритный и распространенный инструмент русского народа, — бесспорный факт. Наши расписные деревянные ложки популярны не только у нас, но и за рубежом. Тысячами вывозят их иностранцы к себе домой в качестве сувениров. Еще бы": "легко, красиво, дешево и сразу «два зайца» — старинный предмет быта и он же — музыкальный инструмент. Деревянные ложки и половники можно купить в магазинах, на базарах или вырезать из сухого дерева самим. Есть народные мастера, специализирующиеся на изготовлении именно музыкальных ложек. Их изделия отличаются несколько большей толщиной, а значит, прочностью и большей звучностью; они используют лучшие породы древесины. Некоторые исполнители навешивают на ложки бубенчики, украшающие цокающий перестук дополнительным звоном."
    },
    {
        "Ссылка на товар": "https://www.muztorg.ru/product/A102621",
        "Ссылка на изображение": "https://www.muztorg.ru/files/3jp/4ew/kho/js4/kgk/84o/0ck/swg/k/3jp4ewkhojs4kgk84o0ckswgk.jpg",
        "Категория товара": "Музыкальные ложки",
        "Наименование": "Мастерская Сереброва бр-лж-06 Ложки веерные",
        "Артикул": "A102621",
        "Наличие": "В наличии",
        "Краткое описание": "Ложки веерные",
        "Цена": "1041",
        "Цена по акции": "Мастерская Сереброва бр-лж-06 Ложки веерные",
        "Начальная цена аренды в день": "Аренды нет",
        "Рейтинг": "Оценок нет",
        "Полное описание": "Нет"
    },
    {
        "Ссылка на товар": "https://www.muztorg.ru/product/A102622",
        "Ссылка на изображение": "https://www.muztorg.ru/files/p42/tz6/ouk/j4s/sw0/4og/0c0/8ko/p42tz6oukj4ssw04og0c08ko.jpg",
        "Категория товара": "Музыкальные ложки",
        "Наименование": "Мастерская Сереброва бр-лж-07 Ложки веерные с бубенцами",
        "Артикул": "A102622",
        "Наличие": "В наличии",
        "Краткое описание": "Ложки веерные с бубенцами",
        "Цена": "1092",
        "Цена по акции": "Мастерская Сереброва бр-лж-07 Ложки веерные с бубенцами",
        "Начальная цена аренды в день": "Аренды нет",
        "Рейтинг": "Оценок нет",
        "Полное описание": "Кто и когда первый додумался превратить наши обыкновенные столовые ложки в ударный инструмент, сказать теперь совершенно невозможно. Но то, что это и прежде и теперь самый простой, самый колоритный и распространенный инструмент русского народа, — бесспорный факт.Некоторые исполнители навешивают на ложки бубенчики, украшающие цокающий перестук дополнительным звоном.",
        "Наши расписные деревянные ложки популярны не только у нас, но и за рубежом. Тысячами вывозят их иностранцы к себе домой в качестве сувениров. Еще бы": "легко, красиво, дешево и сразу «два зайца» — старинный предмет быта и он же — музыкальный инструмент. Деревянные ложки и половники можно купить в магазинах, на базарах или вырезать из сухого дерева самим. Есть народные мастера, специализирующиеся на изготовлении именно музыкальных ложек. Их изделия отличаются несколько большей толщиной, а значит, прочностью и большей звучностью; они используют лучшие породы древесины."
    },
    {
        "Ссылка на товар": "https://www.muztorg.ru/product/A102623",
        "Ссылка на изображение": "https://www.muztorg.ru/files/aq4/6xv/x4f/94w/8k4/co4/gc4/k44/c/aq46xvx4f94w8k4co4gc4k44c.jpg",
        "Категория товара": "Музыкальные ложки",
        "Наименование": "Мастерская Сереброва бр-лж-08 Ложки веерные `пятерка.",
        "Артикул": "A102623",
        "Наличие": "В наличии",
        "Краткое описание": "Ложки веерные \"пятерка\"",
        "Цена": "1420",
        "Цена по акции": "Мастерская Сереброва бр-лж-08 Ложки веерные `пятерка.",
        "Начальная цена аренды в день": "Аренды нет",
        "Рейтинг": "Оценок нет",
        "Полное описание": "",
        "Кто и когда первый додумался превратить наши обыкновенные столовые ложки в ударный инструмент, сказать теперь совершенно невозможно. Но то, что это и прежде и теперь самый простой, самый колоритный и распространенный инструмент русского народа, — бесспорный факт. Наши расписные деревянные ложки популярны не только у нас, но и за рубежом. Тысячами вывозят их иностранцы к себе домой в качестве сувениров. Еще бы": "легко, красиво, дешево и сразу «два зайца» — старинный предмет быта и он же — музыкальный инструмент. Деревянные ложки и половники можно купить в магазинах, на базарах или вырезать из сухого дерева самим. Есть народные мастера, специализирующиеся на изготовлении именно музыкальных ложек. Их изделия отличаются несколько большей толщиной, а значит, прочностью и большей звучностью; они используют лучшие породы древесины. Некоторые исполнители навешивают на ложки бубенчики, украшающие цокающий перестук дополнительным звоном."
    },
    {
        "Ссылка на товар": "https://www.muztorg.ru/product/A102624",
        "Ссылка на изображение": "https://www.muztorg.ru/files/63c/adh/frb/ew4/g0w/o4k/cso/gw8/4/63cadhfrbew4g0wo4kcsogw84.jpg",
        "Категория товара": "Музыкальные ложки",
        "Наименование": "Мастерская Сереброва бр-лж-10 Ложка кленовая, дубовая",
        "Артикул": "A102624",
        "Наличие": "В наличии",
        "Краткое описание": "Ложка кленовая, дубовая",
        "Цена": "411",
        "Цена по акции": "Мастерская Сереброва бр-лж-10 Ложка кленовая, дубовая",
        "Начальная цена аренды в день": "Аренды нет",
        "Рейтинг": "Оценок нет",
        "Полное описание": "Нет"
    },
    {
        "Ссылка на товар": "https://www.muztorg.ru/product/A102691",
        "Ссылка на изображение": "https://www.muztorg.ru/files/3tf/m3x/7a5/544/g80/08s/go0/8gw/3tfm3x7a5544g8008sgo08gw0.jpg",
        "Категория товара": "Музыкальные ложки",
        "Наименование": "Мастерская Сереброва к1-лж-01 Ложка",
        "Артикул": "A102691",
        "Наличие": "В наличии",
        "Краткое описание": "Ложка",
        "Цена": "461",
        "Цена по акции": "Мастерская Сереброва к1-лж-01 Ложка",
        "Начальная цена аренды в день": "Аренды нет",
        "Рейтинг": "Оценок нет",
        "Полное описание": "Обычно в игре одного исполнителя используются три ложки. Две из них закладываются между пальцами левой руки, третья берется в правую. Первые две служат как бы двойной «наковальней», по которой бьют третьей ложкой. Причем бьют скользящим ударом с одной чашечки на другую, тут же еще раз прихлопывая ими при помощи пальцев левой руки. Получается все время многозвучный ажурный ритмический рисунок. Иногда, при игре сидя, в ногах зажимают два-три, а то и четыре половника, по которым также периодически ударяют ложкой или проводят ею глиссандо.Освоение игры на ложках требует некоторого труда и терпения. Разучивать тот или иной, особенно сложный, ритмический рисунок следует вначале медленно, добиваясь автоматизма в движениях. Описанная выше хватка является основной, но не единственной. Мастера-виртуозы очень ловко и разнообразно чередуют удары правой руки о левую, левой о колено или плечо в сочетании с ударами по половникам. Ложечник В. С. Морозов, артист оркестра хора им. Пятницкого, за свою неподражаемую игру на ложках и других народных инструментах был удостоен почетного звания заслуженного артиста РСФСР. Мастерство даже в таком, казалось бы, шуточном деле всегда высоко ценится нашим народом.",
        "Кто и когда первый додумался превратить наши обыкновенные столовые ложки в ударный инструмент, сказать теперь совершенно невозможно. Но то, что это и прежде и теперь самый простой, самый колоритный и распространенный инструмент русского народа, — бесспорный факт. Наши расписные деревянные ложки популярны не только у нас, но и за рубежом. Тысячами вывозят их иностранцы к себе домой в качестве сувениров. Еще бы": "легко, красиво, дешево и сразу «два зайца» — старинный предмет быта и он же — музыкальный инструмент. Деревянные ложки и половники можно купить в магазинах, на базарах или вырезать из сухого дерева самим. Есть народные мастера, специализирующиеся на изготовлении именно музыкальных ложек. Их изделия отличаются несколько большей толщиной, а значит, прочностью и большей звучностью; они используют лучшие породы древесины. Некоторые исполнители навешивают на ложки бубенчики, украшающие цокающий перестук дополнительным звоном."
    },
    {
        "Ссылка на товар": "https://www.muztorg.ru/product/A102701",
        "Ссылка на изображение": "https://www.muztorg.ru/files/9c2/tcs/6tn/sgs/cg8/ssg/k80/gg8/o/9c2tcs6tnsgscg8ssgk80gg8o.jpg",
        "Категория товара": "Музыкальные ложки",
        "Наименование": "Мастерская Сереброва к2-лж-01 Ложка",
        "Артикул": "A102701",
        "Наличие": "\n                В наличии, по предоплате                \n\n\n\n                    Товар в наличии на центральном складе. Будет доставлен после предоплаты\n                \n",
        "Краткое описание": "Ложка",
        "Цена": "281",
        "Цена по акции": "Мастерская Сереброва к2-лж-01 Ложка",
        "Начальная цена аренды в день": "Аренды нет",
        "Рейтинг": "Оценок нет",
        "Полное описание": "Кто и когда первый додумался превратить наши обыкновенные столовые ложки в ударный инструмент, сказать теперь совершенно невозможно. Но то, что это и прежде и теперь самый простой, самый колоритный и распространенный инструмент русского народа, — бесспорный факт.Есть народные мастера, специализирующиеся на изготовлении именно музыкальных ложек. Их изделия отличаются несколько большей толщиной, а значит, прочностью и большей звучностью; они используют лучшие породы древесины. Некоторые исполнители навешивают на ложки бубенчики, украшающие цокающий перестук дополнительным звоном.Обычно в игре одного исполнителя используются три ложки. Две из них закладываются между пальцами левой руки, третья берется в правую. Первые две служат как бы двойной «наковальней», по которой бьют третьей ложкой. Причем бьют скользящим ударом с одной чашечки на другую, тут же еще раз прихлопывая ими при помощи пальцев левой руки. Получается все время многозвучный ажурный ритмический рисунок. Иногда, при игре сидя, в ногах зажимают два-три, а то и четыре половника, по которым также периодически ударяют ложкой или проводят ею глиссандо.Освоение игры на ложках требует некоторого труда и терпения. Разучивать тот или иной, особенно сложный, ритмический рисунок следует вначале медленно, добиваясь автоматизма в движениях. Описанная выше хватка является основной, но не единственной. Мастера-виртуозы очень ловко и разнообразно чередуют удары правой руки о левую, левой о колено или плечо в сочетании с ударами по половникам.",
        "Наши расписные деревянные ложки популярны не только у нас, но и за рубежом. Тысячами вывозят их иностранцы к себе домой в качестве сувениров. Еще бы": "легко, красиво, дешево и сразу «два зайца» — старинный предмет быта и он же — музыкальный инструмент. Деревянные ложки и половники можно купить в магазинах, на базарах или вырезать из сухого дерева самим."
    },
    {
        "Ссылка на товар": "https://www.muztorg.ru/product/A102703",
        "Ссылка на изображение": "https://www.muztorg.ru/files/bbf/b25/tej/54o/oo4/sw0/4c4/wws/bbfb25tej54ooo4sw04c4wws.jpg",
        "Категория товара": "Музыкальные ложки",
        "Наименование": "Мастерская Сереброва к2-лж-08 Ложки веерные `пятерка` Новинка",
        "Артикул": "A102703",
        "Наличие": "В наличии",
        "Краткое описание": "Ложки веерные \"пятерка\" Новинка",
        "Цена": "2286",
        "Цена по акции": "Мастерская Сереброва к2-лж-08 Ложки веерные `пятерка` Новинка",
        "Начальная цена аренды в день": "Аренды нет",
        "Рейтинг": "Оценок нет",
        "Полное описание": "Нет"
    },
    {
        "Ссылка на товар": "https://www.muztorg.ru/product/A102704",
        "Ссылка на изображение": "https://www.muztorg.ru/files/dps/6ky/mep/lw0/swc/wog/0os/wsk/8/dps6kymeplw0swcwog0oswsk8.jpg",
        "Категория товара": "Музыкальные ложки",
        "Наименование": "Мастерская Сереброва к2-лж-09 Ложки веерные `пятерка` с бубенцами Новинка",
        "Артикул": "A102704",
        "Наличие": "В наличии",
        "Краткое описание": "Ложки веерные \"пятерка\" с бубенцами Новинка",
        "Цена": "2484",
        "Цена по акции": "Мастерская Сереброва к2-лж-09 Ложки веерные `пятерка` с бубенцами Новинка",
        "Начальная цена аренды в день": "Аренды нет",
        "Рейтинг": "Оценок нет",
        "Полное описание": "Нет"
    },
    {
        "Ссылка на товар": "https://www.muztorg.ru/product/A102705",
        "Ссылка на изображение": "https://www.muztorg.ru/files/1qb/kq2/usy/18k/ow4/oc8/coo/c0s/o/1qbkq2usy18kow4oc8cooc0so.jpg",
        "Категория товара": "Музыкальные ложки",
        "Наименование": "Мастерская Сереброва к2-лж-11 Ложка длинная с бубенцами",
        "Артикул": "A102705",
        "Наличие": "В наличии",
        "Краткое описание": "Ложка длинная с бубенцами",
        "Цена": "417",
        "Цена по акции": "Мастерская Сереброва к2-лж-11 Ложка длинная с бубенцами",
        "Начальная цена аренды в день": "Аренды нет",
        "Рейтинг": "Оценок нет",
        "Полное описание": "",
        "Кто и когда первый додумался превратить наши обыкновенные столовые ложки в ударный инструмент, сказать теперь совершенно невозможно. Но то, что это и прежде и теперь самый простой, самый колоритный и распространенный инструмент русского народа, — бесспорный факт. Наши расписные деревянные ложки популярны не только у нас, но и за рубежом. Тысячами вывозят их иностранцы к себе домой в качестве сувениров. Еще бы": "легко, красиво, дешево и сразу «два зайца» — старинный предмет быта и он же — музыкальный инструмент. Деревянные ложки и половники можно купить в магазинах, на базарах или вырезать из сухого дерева самим. Есть народные мастера, специализирующиеся на изготовлении именно музыкальных ложек. Их изделия отличаются несколько большей толщиной, а значит, прочностью и большей звучностью; они используют лучшие породы древесины. Некоторые исполнители навешивают на ложки бубенчики, украшающие цокающий перестук дополнительным звоном."
    },
    {
        "Ссылка на товар": "https://www.muztorg.ru/product/A102706",
        "Ссылка на изображение": "https://www.muztorg.ru/files/2mo/nnh/rbs/oo4/os4/ows/ggw/kw0/2monnhrbsoo4os4owsggwkw00.jpg",
        "Категория товара": "Музыкальные ложки",
        "Наименование": "Мастерская Сереброва к2-лж-10 Ложка длинная",
        "Артикул": "A102706",
        "Наличие": "В наличии",
        "Краткое описание": "Ложка длинная",
        "Цена": "344",
        "Цена по акции": "Мастерская Сереброва к2-лж-10 Ложка длинная",
        "Начальная цена аренды в день": "Аренды нет",
        "Рейтинг": "Оценок нет",
        "Полное описание": "",
        "Наши расписные деревянные ложки популярны не только у нас, но и за рубежом. Тысячами вывозят их иностранцы к себе домой в качестве сувениров. Еще бы": "легко, красиво, дешево и сразу «два зайца» — старинный предмет быта и он же — музыкальный инструмент. Деревянные ложки и половники можно купить в магазинах, на базарах или вырезать из сухого дерева самим. Есть народные мастера, специализирующиеся на изготовлении именно музыкальных ложек. Их изделия отличаются несколько большей толщиной, а значит, прочностью и большей звучностью; они используют лучшие породы древесины. Некоторые исполнители навешивают на ложки бубенчики, украшающие цокающий перестук дополнительным звоном."
    },
    {
        "Ссылка на товар": "https://www.muztorg.ru/product/A102739",
        "Ссылка на изображение": "https://www.muztorg.ru/files/2p4/w08/5nd/x44/4gw/8ow/www/swg/o/2p4w085ndx444gw8owwwwswgo.jpg",
        "Категория товара": "Музыкальные ложки",
        "Наименование": "Мастерская Сереброва су-лж-01 Ложка малая",
        "Артикул": "A102739",
        "Наличие": "В наличии",
        "Краткое описание": "Ложка малая",
        "Цена": "169",
        "Цена по акции": "Мастерская Сереброва су-лж-01 Ложка малая",
        "Начальная цена аренды в день": "Аренды нет",
        "Рейтинг": "Оценок нет",
        "Полное описание": "Ложка сувенирнаяЛожка деревянная размером с чайную ложку 14 см х 3,5 см"
    },
    {
        "Ссылка на товар": "https://www.muztorg.ru/product/A102743",
        "Ссылка на изображение": "https://www.muztorg.ru/files/dcl/50a/awg/9sg/cok/o8o/k8c/gsc/w/dcl50aawg9sgcoko8ok8cgscw.jpg",
        "Категория товара": "Музыкальные ложки",
        "Наименование": "Мастерская Сереброва т1-лж-01 Ложка",
        "Артикул": "A102743",
        "Наличие": "В наличии",
        "Краткое описание": "Ложка",
        "Цена": "382",
        "Цена по акции": "Мастерская Сереброва т1-лж-01 Ложка",
        "Начальная цена аренды в день": "Аренды нет",
        "Рейтинг": "Оценок нет",
        "Полное описание": "Обычно в игре одного исполнителя используются три ложки. Две из них закладываются между пальцами левой руки, третья берется в правую. Первые две служат как бы двойной «наковальней», по которой бьют третьей ложкой. Причем бьют скользящим ударом с одной чашечки на другую, тут же еще раз прихлопывая ими при помощи пальцев левой руки. Получается все время многозвучный ажурный ритмический рисунок. Иногда, при игре сидя, в ногах зажимают два-три, а то и четыре половника, по которым также периодически ударяют ложкой или проводят ею глиссандо.Освоение игры на ложках требует некоторого труда и терпения. Разучивать тот или иной, особенно сложный, ритмический рисунок следует вначале медленно, добиваясь автоматизма в движениях. Описанная выше хватка является основной, но не единственной. Мастера-виртуозы очень ловко и разнообразно чередуют удары правой руки о левую, левой о колено или плечо в сочетании с ударами по половникам. Ложечник В. С. Морозов, артист оркестра хора им. Пятницкого, за свою неподражаемую игру на ложках и других народных инструментах был удостоен почетного звания заслуженного артиста РСФСР. Мастерство даже в таком, казалось бы, шуточном деле всегда высоко ценится нашим народом.",
        "Кто и когда первый додумался превратить наши обыкновенные столовые ложки в ударный инструмент, сказать теперь совершенно невозможно. Но то, что это и прежде и теперь самый простой, самый колоритный и распространенный инструмент русского народа, — бесспорный факт. Наши расписные деревянные ложки популярны не только у нас, но и за рубежом. Тысячами вывозят их иностранцы к себе домой в качестве сувениров. Еще бы": "легко, красиво, дешево и сразу «два зайца» — старинный предмет быта и он же — музыкальный инструмент. Деревянные ложки и половники можно купить в магазинах, на базарах или вырезать из сухого дерева самим. Есть народные мастера, специализирующиеся на изготовлении именно музыкальных ложек. Их изделия отличаются несколько большей толщиной, а значит, прочностью и большей звучностью; они используют лучшие породы древесины. Некоторые исполнители навешивают на ложки бубенчики, украшающие цокающий перестук дополнительным звоном."
    },
    {
        "Ссылка на товар": "https://www.muztorg.ru/product/A102752",
        "Ссылка на изображение": "https://www.muztorg.ru/files/bju/rgm/bce/bk0/48w/wsg/k4o/s4w/8/bjurgmbcebk048wwsgk4os4w8.jpg",
        "Категория товара": "Музыкальные ложки",
        "Наименование": "Мастерская Сереброва т2-лж-01 Ложка",
        "Артикул": "A102752",
        "Наличие": "\n                В наличии, по предоплате                \n\n\n\n                    Товар в наличии на центральном складе. Будет доставлен после предоплаты\n                \n",
        "Краткое описание": "Ложка",
        "Цена": "254",
        "Цена по акции": "Мастерская Сереброва т2-лж-01 Ложка",
        "Начальная цена аренды в день": "Аренды нет",
        "Рейтинг": "Оценок нет",
        "Полное описание": "Нет"
    },
    {
        "Ссылка на товар": "https://www.muztorg.ru/product/A102754",
        "Ссылка на изображение": "https://www.muztorg.ru/files/9mq/x7b/gw9/3k8/4cw/08k/wco/ss0/s/9mqx7bgw93k84cw08kwcoss0s.jpg",
        "Категория товара": "Музыкальные ложки",
        "Наименование": "Мастерская Сереброва т2-лж-10 Ложка длинная",
        "Артикул": "A102754",
        "Наличие": "В наличии",
        "Краткое описание": "Ложка длинная",
        "Цена": "288",
        "Цена по акции": "Мастерская Сереброва т2-лж-10 Ложка длинная",
        "Начальная цена аренды в день": "Аренды нет",
        "Рейтинг": "Оценок нет",
        "Полное описание": "Нет"
    },
    {
        "Ссылка на товар": "https://www.muztorg.ru/product/A102755",
        "Ссылка на изображение": "https://www.muztorg.ru/files/95a/1pe/5np/xc0/00c/wcg/w0g/gwk/s/95a1pe5npxc000cwcgw0ggwks.jpg",
        "Категория товара": "Музыкальные ложки",
        "Наименование": "Мастерская Сереброва т2-лж-11 Ложка длинная с бубенцами",
        "Артикул": "A102755",
        "Наличие": "В наличии",
        "Краткое описание": "Ложка длинная с бубенцами",
        "Цена": "347",
        "Цена по акции": "Мастерская Сереброва т2-лж-11 Ложка длинная с бубенцами",
        "Начальная цена аренды в день": "Аренды нет",
        "Рейтинг": "Оценок нет",
        "Полное описание": "Нет"
    },
    {
        "Ссылка на товар": "https://www.muztorg.ru/product/A116040",
        "Ссылка на изображение": "https://www.muztorg.ru/files/2rj/k53/i9o/88w/oc8/oww/scw/488/w/2rjk53i9o88woc8owwscw488w.jpeg",
        "Категория товара": "Музыкальные ложки",
        "Наименование": "Хохлома LHL6301 Деревянная ложка полубаская, без росписи, покрытая лаком",
        "Артикул": "A116040",
        "Наличие": "В наличии",
        "Краткое описание": "Деревянная ложка полубаская, без росписи, покрытая лаком",
        "Цена": "70",
        "Цена по акции": "Хохлома LHL6301 Деревянная ложка полубаская, без росписи, покрытая лаком",
        "Начальная цена аренды в день": "Аренды нет",
        "Рейтинг": "Оценок нет",
        "Полное описание": "LHL6301 Деревянная ложка полубаская, без росписи, покрытая лаком, Хохлома",
        "Материал": "береза.",
        "Длина": "19см.",
        "Ширина черпачка": "6см."
    },
    {
        "Ссылка на товар": "https://www.muztorg.ru/product/A116043",
        "Ссылка на изображение": "https://www.muztorg.ru/files/8vg/6fj/bzu/c08/gko/oko/4kc/4kw/c/8vg6fjbzuc08gkooko4kc4kwc.jpeg",
        "Категория товара": "Музыкальные ложки",
        "Наименование": "Хохлома LHL6502 Деревянная ложка маленькая, роспись `Чернушка.",
        "Артикул": "A116043",
        "Наличие": "В наличии",
        "Краткое описание": "Деревянная ложка маленькая, роспись \"Чернушка\"",
        "Цена": "60",
        "Цена по акции": "Хохлома LHL6502 Деревянная ложка маленькая, роспись `Чернушка.",
        "Начальная цена аренды в день": "Аренды нет",
        "Рейтинг": "Оценок нет",
        "Полное описание": "LHL6502 Деревянная ложка маленькая, роспись \"Чернушка\", Хохлома",
        "Материал": "береза.",
        "Длина": "14,7см.",
        "Ширина черпачка": "3,5см."
    },
    {
        "Ссылка на товар": "https://www.muztorg.ru/product/A116044",
        "Ссылка на изображение": "https://www.muztorg.ru/files/12f/x0p/463/9b4/kss/ccc/g00/wc4/12fx0p4639b4ksscccg00wc40.jpeg",
        "Категория товара": "Музыкальные ложки",
        "Наименование": "Хохлома LHL7102 Деревянная ложка маленькая, роспись `Золото.",
        "Артикул": "A116044",
        "Наличие": "В наличии",
        "Краткое описание": "Деревянная ложка маленькая, роспись \"Золото\"",
        "Цена": "80",
        "Цена по акции": "Хохлома LHL7102 Деревянная ложка маленькая, роспись `Золото.",
        "Начальная цена аренды в день": "Аренды нет",
        "Рейтинг": "Оценок нет",
        "Полное описание": "LHL7102 Деревянная ложка маленькая, роспись \"Золото\", Хохлома",
        "Материал": "береза.",
        "Длина": "14,7см.",
        "Ширина черпачка": "3,5см."
    },
    {
        "Ссылка на товар": "https://www.muztorg.ru/product/A116100",
        "Ссылка на изображение": "https://www.muztorg.ru/files/5fb/za3/pc7/0w8/00w/okw/wwg/8oo/5fbza3pc70w800wokwwwg8oo0.jpeg",
        "Категория товара": "Музыкальные ложки",
        "Наименование": "Хохлома LHL6703 Деревянная ложка полубаская, роспись `Лисичка.",
        "Артикул": "A116100",
        "Наличие": "В наличии",
        "Краткое описание": "Деревянная ложка полубаская, роспись \"Лисичка\"",
        "Цена": "120",
        "Цена по акции": "Хохлома LHL6703 Деревянная ложка полубаская, роспись `Лисичка.",
        "Начальная цена аренды в день": "Аренды нет",
        "Рейтинг": "Оценок нет",
        "Полное описание": "LHL6703 Деревянная ложка полубаская, роспись \"Лисичка\", Хохлома",
        "Материал": "береза.",
        "Длина": "19см.",
        "Ширина черпачка": "6см."
    },
    {
        "Ссылка на товар": "https://www.muztorg.ru/product/A116139",
        "Ссылка на изображение": "https://www.muztorg.ru/files/dsk/zpe/453/hss/4wk/8cc/gs4/ksg/dskzpe453hss4wk8ccgs4ksg0.jpeg",
        "Категория товара": "Музыкальные ложки",
        "Наименование": "Хохлома LHL6802 Ложка чайная `Краснушка.",
        "Артикул": "A116139",
        "Наличие": "В наличии",
        "Краткое описание": "Ложка чайная \"Краснушка\"",
        "Цена": "70",
        "Цена по акции": "Хохлома LHL6802 Ложка чайная `Краснушка.",
        "Начальная цена аренды в день": "Аренды нет",
        "Рейтинг": "Оценок нет",
        "Полное описание": "LHL6802 Ложка чайная \"Краснушка\", Хохлома",
        "Материал": "береза.",
        "Длина": "14,7см.",
        "Ширина черпачка": "3,5см."
    },
    {
        "Ссылка на товар": "https://www.muztorg.ru/product/A066331",
        "Ссылка на изображение": "https://www.muztorg.ru/files/56p/uys/koh/400/ooc/gc4/kwo/84s/s/56puyskoh400oocgc4kwo84ss.jpg",
        "Категория товара": "Музыкальные ложки",
        "Наименование": "YARA MS-2KR",
        "Артикул": "A066331",
        "Наличие": "\n                В наличии в другом городе                \n                    Товар может быть доставлен из магазина в другом регионе\n                                    \n",
        "Краткое описание": "Музыкальные ложки `Царские`, пара, цвет-красный, МЛХ, материал - осина, береза",
        "Цена": "265",
        "Цена по акции": "YARA MS-2KR",
        "Начальная цена аренды в день": "Аренды нет",
        "Рейтинг": "Оценок нет",
        "Полное описание": "(не задано)"
    }
]