[
    {
        "Ссылка на товар": "https://www.muztorg.ru/product/A137074",
        "Ссылка на изображение": "https://www.muztorg.ru/files/4et/n51/jat/xgk/s88/4o4/cg4/ooo/w/4etn51jatxgks884o4cg4ooow.jpg",
        "Категория товара": "Аксессуары",
        "Наименование": "SanDisk Cruzer Snap",
        "Артикул": "A137074",
        "Наличие": "В наличии",
        "Краткое описание": "64ГБ Флеш-накопитель",
        "Цена": "799",
        "Цена по акции": "SanDisk Cruzer Snap",
        "Начальная цена аренды в день": "Аренды нет",
        "Рейтинг": "Оценок нет",
        "Полное описание": "Память USB Flash SanDisk Cruzer Snap [SDCZ62-064G-G35] емкостью 64 ГБ имеет выдвижную конструкцию и пластиковый корпус. Такая конфигурация обеспечивает хранилищу информации защиту от механических повреждений. Скорость записи и чтения для модели составляет соответственно 4 и 16 МБ/с. С использованием накопителя памяти USB Flash SanDisk Cruzer Snap [SDCZ62-064G-G35] ваши документы, аудиозаписи, фотографии всегда будут под рукой где угодно даже без доступа к интернету. За счет объема карты хранить на нем можно большое количество файлов."
    },
    {
        "Ссылка на товар": "https://www.muztorg.ru/product/A124889",
        "Ссылка на изображение": "https://www.muztorg.ru/files/bhr/5sk/img/tw8/8go/0s0/44s/40s/g/bhr5skimgtw88go0s044s40sg.jpg",
        "Категория товара": "Аксессуары",
        "Наименование": "K&M 19800-000-55",
        "Артикул": "A124889",
        "Наличие": "В наличии",
        "Краткое описание": "универсальная настольная подставка для смартфона и планшета с нескользящим покрытием, диапазон зажима 130-240 мм, основание состоит из 4 нескользящих ножек и имеет отверстие для кабеля, держатель вращается на 360 градусов, цвет черный",
        "Цена": "5940",
        "Цена по акции": "K&M 19800-000-55",
        "Начальная цена аренды в день": "Аренды нет",
        "Рейтинг": "Оценок нет",
        "Полное описание": "Нет"
    },
    {
        "Ссылка на товар": "https://www.muztorg.ru/product/A114486",
        "Ссылка на изображение": "https://www.muztorg.ru/files/79q/isd/p3z/i0w/kw0/4ks/o8w/wk0/8/79qisdp3zi0wkw04kso8wwk08.jpg",
        "Категория товара": "Аксессуары",
        "Наименование": "Mophie 3-in-1 Cable USB-A to Lightning/Micro USB/USB-C 1m - Black",
        "Артикул": "A114486",
        "Наличие": "\n                Нет в наличии                \n\n\n\n                    Товара нет в наличии в сети Музторг\n                \n",
        "Краткое описание": "Кабель",
        "Цена": "2990",
        "Цена по акции": "Mophie 3-in-1 Cable USB-A to Lightning/Micro USB/USB-C 1m - Black",
        "Начальная цена аренды в день": "Аренды нет",
        "Рейтинг": "Оценок нет",
        "Полное описание": "Кабель 3в1 Mophie USB-A to Lightning/Micro USB/USB-C. Длина 1м. Цвет черный."
    },
    {
        "Ссылка на товар": "https://www.muztorg.ru/product/A114487",
        "Ссылка на изображение": "https://www.muztorg.ru/files/8xu/ng0/apm/zgg/wg0/c00/skw/css/8/8xung0apmzggwg0c00skwcss8.jpg",
        "Категория товара": "Аксессуары",
        "Наименование": "Mophie 3-in-1 Cable USB-A to Lightning/Micro USB/USB-C 1m - White",
        "Артикул": "A114487",
        "Наличие": "\n                Нет в наличии                \n\n\n\n                    Товара нет в наличии в сети Музторг\n                \n",
        "Краткое описание": "Кабель",
        "Цена": "2990",
        "Цена по акции": "Mophie 3-in-1 Cable USB-A to Lightning/Micro USB/USB-C 1m - White",
        "Начальная цена аренды в день": "Аренды нет",
        "Рейтинг": "Оценок нет",
        "Полное описание": "Кабель 3в1 Mophie USB-A to Lightning/Micro USB/USB-C. Длина 1м. Цвет белый."
    },
    {
        "Ссылка на товар": "https://www.muztorg.ru/product/A114491",
        "Ссылка на изображение": "https://www.muztorg.ru/files/9cr/hls/010/gsg/wog/ksk/occ/kgw/9crhls010gsgwogkskocckgw0.jpg",
        "Категория товара": "Аксессуары",
        "Наименование": "Mophie USB-A to Lightning Cable 3m - Black",
        "Артикул": "A114491",
        "Наличие": "\n                Нет в наличии                \n\n\n\n                    Товара нет в наличии в сети Музторг\n                \n",
        "Краткое описание": "Кабель",
        "Цена": "2290",
        "Цена по акции": "Mophie USB-A to Lightning Cable 3m - Black",
        "Начальная цена аренды в день": "Аренды нет",
        "Рейтинг": "Оценок нет",
        "Полное описание": "Кабель Mophie USB-A to Lightning. Длина 3м. Цвет черный."
    },
    {
        "Ссылка на товар": "https://www.muztorg.ru/product/A114492",
        "Ссылка на изображение": "https://www.muztorg.ru/files/ejn/60d/o2d/hc0/owc/gwc/owk/0cc/ejn60do2dhc0owcgwcowk0cc0.jpg",
        "Категория товара": "Аксессуары",
        "Наименование": "Mophie USB-A to Lightning Cable 9cm - Black",
        "Артикул": "A114492",
        "Наличие": "\n                Нет в наличии                \n\n\n\n                    Товара нет в наличии в сети Музторг\n                \n",
        "Краткое описание": "Кабель",
        "Цена": "1790",
        "Цена по акции": "Mophie USB-A to Lightning Cable 9cm - Black",
        "Начальная цена аренды в день": "Аренды нет",
        "Рейтинг": "Оценок нет",
        "Полное описание": "Кабель Mophie USB-A to Lightning. Длина 9см. Цвет черный."
    },
    {
        "Ссылка на товар": "https://www.muztorg.ru/product/A114493",
        "Ссылка на изображение": "https://www.muztorg.ru/files/bi5/kmq/8wj/ls0/c0k/g4k/oog/c40/o/bi5kmq8wjls0c0kg4koogc40o.jpg",
        "Категория товара": "Аксессуары",
        "Наименование": "Mophie USB-A to Lightning Cable 9cm - White",
        "Артикул": "A114493",
        "Наличие": "\n                Нет в наличии                \n\n\n\n                    Товара нет в наличии в сети Музторг\n                \n",
        "Краткое описание": "Кабель",
        "Цена": "1790",
        "Цена по акции": "Mophie USB-A to Lightning Cable 9cm - White",
        "Начальная цена аренды в день": "Аренды нет",
        "Рейтинг": "Оценок нет",
        "Полное описание": "Кабель Mophie USB-A to Lightning. Длина 9см. Цвет белый."
    },
    {
        "Ссылка на товар": "https://www.muztorg.ru/product/A114496",
        "Ссылка на изображение": "https://www.muztorg.ru/files/5wv/071/6qx/5gc/04c/4kc/w4k/80g/8/5wv0716qx5gc04c4kcw4k80g8.jpg",
        "Категория товара": "Аксессуары",
        "Наименование": "Mophie USB-A to USB-C Cable 3m - White",
        "Артикул": "A114496",
        "Наличие": "\n                Нет в наличии                \n\n\n\n                    Товара нет в наличии в сети Музторг\n                \n",
        "Краткое описание": "Кабель",
        "Цена": "1390",
        "Цена по акции": "Mophie USB-A to USB-C Cable 3m - White",
        "Начальная цена аренды в день": "Аренды нет",
        "Рейтинг": "Оценок нет",
        "Полное описание": "Кабель Mophie USB-A to USB-C. Длина 3м. Цвет белый."
    },
    {
        "Ссылка на товар": "https://www.muztorg.ru/product/A114500",
        "Ссылка на изображение": "https://www.muztorg.ru/files/6v0/ld2/klk/bgg/04o/wsk/8gw/8g0/6v0ld2klkbgg04owsk8gw8g00.jpg",
        "Категория товара": "Аксессуары",
        "Наименование": "Mophie USB-C to USB-C Cable 1,5m - Black",
        "Артикул": "A114500",
        "Наличие": "\n                Нет в наличии                \n\n\n\n                    Товара нет в наличии в сети Музторг\n                \n",
        "Краткое описание": "Кабель",
        "Цена": "2790",
        "Цена по акции": "Mophie USB-C to USB-C Cable 1,5m - Black",
        "Начальная цена аренды в день": "Аренды нет",
        "Рейтинг": "Оценок нет",
        "Полное описание": "Кабель Mophie USB-C to USB-C. Длина 1,5м. Цвет черный."
    },
    {
        "Ссылка на товар": "https://www.muztorg.ru/product/A120657",
        "Ссылка на изображение": "https://www.muztorg.ru/files/dgw/oh0/wto/8gs/wgo/08g/cg8/0sg/4/dgwoh0wto8gswgo08gcg80sg4.jpg",
        "Категория товара": "Аксессуары",
        "Наименование": "XIAOMI NINETYGO Classic Business Backpack",
        "Артикул": "A120657",
        "Наличие": "\n                Нет в наличии                \n\n\n\n                    Товара нет в наличии в сети Музторг\n                \n",
        "Краткое описание": "Рюкзак",
        "Цена": "3090",
        "Цена по акции": "XIAOMI NINETYGO Classic Business Backpack",
        "Начальная цена аренды в день": "Аренды нет",
        "Рейтинг": "Оценок нет",
        "Полное описание": "Материал рюкзака - нейлон марки 1260D, с отличными водоотталкивающими качествами, молния также водонепроницаема. Сам материал лёгкий, износостойкийСпинка выполнена из дышащего материала, облегчающего долгое ношение улучшенной вентиляциейПластиковая основа, улучшающая внешний вид и водоотталкивающие свойства",
        "Ваш лучший бизнес партнёр. Рюкзак Xiaomi никогда не выйдет из моды благодаря классическому дизайну. Отличный чёрный цвет с синими линиями добавляет изюминку дизайну. Он легко подойдёт как к рабочему стилю, так и к повседневной прогулки. С лёгкостью отправляйтесь в бизнес-путешествия благодаря удобству встроенного пространства, внутри рюкзака встроен удобный органайзер для вещей": "Отделение для ноутбука, “мини-офис” для ежедневника и ручек, отдельный карман для смартфона и мелочи. Кроме того, вы обеспечите безопасную транспортировку ваших вещей!Крепление на ручку чемодана, и лямки в виде буквы S для удобства ношения. Ручка выполнена из крепкого материала с комфортным хватом"
    },
    {
        "Ссылка на товар": "https://www.muztorg.ru/product/A119480",
        "Ссылка на изображение": "https://www.muztorg.ru/files/ay0/68i/7k0/j4s/kc4/k8k/oc8/ocg/g/ay068i7k0j4skc4k8koc8ocgg.jpg",
        "Категория товара": "Аксессуары",
        "Наименование": "Rombica AUTO MC02 Quick",
        "Артикул": "A119480",
        "Наличие": "\n                В наличии в другом городе                \n                    Товар может быть доставлен из магазина в другом регионе\n                                    \n",
        "Краткое описание": "Автомобильное зарядное устройство",
        "Цена": "890",
        "Цена по акции": "Rombica AUTO MC02 Quick",
        "Начальная цена аренды в день": "Аренды нет",
        "Рейтинг": "Оценок нет",
        "Полное описание": "",
        "Вход": "12-24В",
        "Версия Quick Charge": "3.0",
        "Ревизия USB Power Delivery": "USB PD Rev.2",
        "Выход(ы)": " ",
        "USB": "5-6В/2.4А; 6-9В/2А; 9-12В/1.5А ",
        "TYPE-C": "5В/2.4А; 9В/2А; 12В/2.5А (30 Ватт максимум)",
        "Материал": " Металл"
    },
    {
        "Ссылка на товар": "https://www.muztorg.ru/product/A137057",
        "Ссылка на изображение": "https://www.muztorg.ru/files/1s6/qek/5o1/zno/o48/gc0/skg/gg8/4/1s6qek5o1znoo48gc0skggg84.jpg",
        "Категория товара": "Аксессуары",
        "Наименование": "QUIK LOK LPH007",
        "Артикул": "A137057",
        "Наличие": "\n                Под заказ                \n\n\n\n                    Доставим товар под заказ. Условия доставки вам сообщит менеджер\n                                      \n",
        "Краткое описание": "напольная подставка для планшета",
        "Цена": "9100",
        "Цена по акции": "QUIK LOK LPH007",
        "Начальная цена аренды в день": "Аренды нет",
        "Рейтинг": "Оценок нет",
        "Полное описание": "Нет"
    },
    {
        "Ссылка на товар": "https://www.muztorg.ru/product/A136469",
        "Ссылка на изображение": "Нет изображения",
        "Категория товара": "Аксессуары",
        "Наименование": "K&M 19805-000-55",
        "Артикул": "A136469",
        "Наличие": "\n                Под заказ                \n\n\n\n                    Доставим товар под заказ. Условия доставки вам сообщит менеджер\n                                      \n",
        "Краткое описание": "универсальный держатель для смартфона и планшета с креплением типа пантограф, вращение 360 градусов, ширина захвата 130 - 224 мм, цвет черный",
        "Цена": "7800",
        "Цена по акции": "K&M 19805-000-55",
        "Начальная цена аренды в день": "Аренды нет",
        "Рейтинг": "Оценок нет",
        "Полное описание": "Нет"
    }
]